fluxpy/__init__.py
fluxpy/core/__init__.py
fluxpy/core/app.py
fluxpy/core/debugger.py
fluxpy/core/orm.py
fluxpy/engine/__init__.py
fluxpy/engine/core.py
fluxpy/extra/__init__.py
fluxpy/widgets/__init__.py
fluxpy/widgets/base.py
fluxpy/widgets/dialogs.py
fluxpy/widgets/input.py
fluxpy/widgets/layout.py
fluxpy/widgets/list_table.py
fluxpy/widgets/media.py
fluxpy/widgets/navigation.py
fluxpy_ui-3.4.1.dist-info/METADATA
fluxpy_ui-3.4.1.dist-info/WHEEL
fluxpy_ui-3.4.1.dist-info/top_level.txt
fluxpy_ui-3.4.1.dist-info/RECORD
