Metadata-Version: 2.1
Name: fluxpy-ui
Version: 3.4.1
Summary: The Ultimate Universal Python UI Framework for Desktop, Web, and Mobile
Home-page: UNKNOWN
Author: FluxPy Team
License: UNKNOWN
Platform: UNKNOWN
Classifier: Programming Language :: Python :: 3
Classifier: License :: OSI Approved :: MIT License
Classifier: Operating System :: OS Independent
Requires-Python: >=3.7
Requires-Dist: PyQt6
Requires-Dist: flask
